aiotfm/__init__.py
aiotfm/__version__.py
aiotfm/client.py
aiotfm/connection.py
aiotfm/enums.py
aiotfm/errors.py
aiotfm/friend.py
aiotfm/inventory.py
aiotfm/message.py
aiotfm/packet.py
aiotfm/player.py
aiotfm/room.py
aiotfm/shop.py
aiotfm/tribe.py
aiotfm/utils/__init__.py
aiotfm/utils/date.py
aiotfm/utils/get_keys.py
aiotfm/utils/locale.py
aiotfm/utils/shakikoo.py
aiotfm-1.4.9.dist-info/LICENSE.txt
aiotfm-1.4.9.dist-info/METADATA
aiotfm-1.4.9.dist-info/WHEEL
aiotfm-1.4.9.dist-info/top_level.txt
aiotfm-1.4.9.dist-info/RECORD
