Metadata-Version: 2.1
Name: aiotfm
Version: 1.4.9
Summary: An asynchronous event based client for Transformice
Author: Athesdrake
Maintainer-email: Athesdrake <athesdrake@gmail.com>
License: MIT License
Project-URL: Homepage, https://github.com/Athesdrake/aiotfm
Project-URL: Bug Reports, https://github.com/Athesdrake/aiotfm/issues
Project-URL: Source, https://github.com/Athesdrake/aiotfm
Keywords: TRANFORMICE,CLIENT,ASYNC,ATELIER801,EVENT
Classifier: Development Status :: 5 - Production/Stable
Classifier: Framework :: AsyncIO
Classifier: Intended Audience :: Developers
Classifier: Programming Language :: Python :: 3
Classifier: Programming Language :: Python :: 3.8
Classifier: Programming Language :: Python :: 3.9
Classifier: Programming Language :: Python :: 3.10
Classifier: Programming Language :: Python :: 3.11
Classifier: Programming Language :: Python :: 3.12
Classifier: Topic :: Software Development :: Libraries
Requires-Python: >=3.8
License-File: LICENSE.txt
Requires-Dist: aiohttp
Provides-Extra: dev
Requires-Dist: pytest ; extra == 'dev'
Requires-Dist: ruff ; extra == 'dev'
